jackattack.py
jackattack-0.0.1.dist-info/METADATA
jackattack-0.0.1.dist-info/WHEEL
jackattack-0.0.1.dist-info/top_level.txt
jackattack-0.0.1.dist-info/RECORD
