Metadata-Version: 2.1
Name: jackattack
Version: 0.0.1
Summary: An attack class for Jack
Home-page: https://github.com/jackrmcshane/jackattack
Author: Jack McShane
Author-email: jackrmcshane@gmail.com
Classifier: Development Status :: 3 - Alpha
Classifier: License :: OSI Approved :: MIT License
Classifier: Natural Language :: English
Classifier: Operating System :: OS Independent
Classifier: Programming Language :: Python :: 3
